{
  "jurisdiction": {
    "country": "us",
    "state": "ms"
  },
  "topic": "rent-increase",
  "rule": {
    "data": {
      "noticeDays": 30,
      "maxIncreasePercent": null,
      "rentControl": false,
      "frequencyLimit": null
    },
    "citations": [
      {
        "statute": "Miss. Code § 89-7-23",
        "url": "",
        "excerpt": "",
        "sourceType": "statute",
        "lastUpdated": "2025-01-01",
        "confidence": 0.8
      }
    ],
    "version": {
      "version": "2025.01",
      "effectiveDate": "2025-01-01",
      "supersedes": null,
      "notes": [
        "Mississippi has no rent control and minimal notice requirements."
      ]
    }
  }
}